cmakelint/__init__.py
cmakelint/__version__.py
cmakelint/main.py
cmakelint-1.4.3.dist-info/LICENSE
cmakelint-1.4.3.dist-info/METADATA
cmakelint-1.4.3.dist-info/WHEEL
cmakelint-1.4.3.dist-info/entry_points.txt
cmakelint-1.4.3.dist-info/top_level.txt
cmakelint-1.4.3.dist-info/RECORD
