Metadata-Version: 2.1
Name: cmakelint
Version: 1.4.3
Summary: Static code checker for CMake files
Home-page: https://github.com/cmake-lint/cmake-lint
Download-URL: https://github.com/cmake-lint/cmake-lint
Author: Richard Quirk
Author-email: richard.quirk@gmail.com
License: Apache 2.0
Keywords: cmake,lint
Classifier: Topic :: Software Development
Classifier: Development Status :: 5 - Production/Stable
Classifier: Environment :: Console
Classifier: Programming Language :: Other
Classifier: Programming Language :: Python
Classifier: License :: OSI Approved :: Apache Software License
License-File: LICENSE
Provides-Extra: dev
Requires-Dist: tox >=3.0.0 ; extra == 'dev'
Requires-Dist: ruff >=0.3.0 ; extra == 'dev'
Requires-Dist: pytest >=8.0.0 ; extra == 'dev'
Requires-Dist: pytest-cov ; extra == 'dev'
Requires-Dist: pyparsing <3 ; extra == 'dev'
Requires-Dist: zipp <=0.5.1 ; extra == 'dev'
Requires-Dist: configparser <=3.7.4 ; extra == 'dev'
Requires-Dist: testfixtures ; extra == 'dev'
Provides-Extra: test
Requires-Dist: pytest >=8.0.0 ; extra == 'test'
Requires-Dist: pytest-cov ; extra == 'test'
Requires-Dist: pyparsing <3 ; extra == 'test'
Requires-Dist: zipp <=0.5.1 ; extra == 'test'
Requires-Dist: configparser <=3.7.4 ; extra == 'test'
Requires-Dist: testfixtures ; extra == 'test'
